odoo9_addon_l10n_es_account_invoice_sequence-9.0.1.0.0-py2.7-nspkg.pth
odoo_addons/l10n_es_account_invoice_sequence/__openerp__.py
odoo_addons/l10n_es_account_invoice_sequence/hooks.py
odoo_addons/l10n_es_account_invoice_sequence/__init__.py
odoo_addons/l10n_es_account_invoice_sequence/README.rst
odoo_addons/l10n_es_account_invoice_sequence/models/account_invoice.py
odoo_addons/l10n_es_account_invoice_sequence/models/account_journal.py
odoo_addons/l10n_es_account_invoice_sequence/models/__init__.py
odoo_addons/l10n_es_account_invoice_sequence/models/account_chart_template.py
odoo_addons/l10n_es_account_invoice_sequence/i18n/es.po
odoo_addons/l10n_es_account_invoice_sequence/i18n/bg.po
odoo_addons/l10n_es_account_invoice_sequence/i18n/gl.po
odoo_addons/l10n_es_account_invoice_sequence/i18n/ca.po
odoo_addons/l10n_es_account_invoice_sequence/i18n/sl.po
odoo_addons/l10n_es_account_invoice_sequence/views/account_journal_view.xml
odoo_addons/l10n_es_account_invoice_sequence/wizards/__init__.py
odoo_addons/l10n_es_account_invoice_sequence/wizards/wizard_multi_charts_accounts.py
odoo_addons/l10n_es_account_invoice_sequence/data/sequence_data.xml
odoo_addons/l10n_es_account_invoice_sequence/tests/__init__.py
odoo_addons/l10n_es_account_invoice_sequence/tests/test_invoice_sequence.py
odoo_addons/l10n_es_account_invoice_sequence/tests/test_create_chart.py
odoo9_addon_l10n_es_account_invoice_sequence-9.0.1.0.0.dist-info/top_level.txt
odoo9_addon_l10n_es_account_invoice_sequence-9.0.1.0.0.dist-info/WHEEL
odoo9_addon_l10n_es_account_invoice_sequence-9.0.1.0.0.dist-info/RECORD
odoo9_addon_l10n_es_account_invoice_sequence-9.0.1.0.0.dist-info/metadata.json
odoo9_addon_l10n_es_account_invoice_sequence-9.0.1.0.0.dist-info/DESCRIPTION.rst
odoo9_addon_l10n_es_account_invoice_sequence-9.0.1.0.0.dist-info/METADATA
odoo9_addon_l10n_es_account_invoice_sequence-9.0.1.0.0.dist-info/namespace_packages.txt
