Metadata-Version: 2.0
Name: odoo9-addon-l10n-es-account-invoice-sequence
Version: 9.0.1.0.0
Summary: Secuencia para facturas separada de la secuencia de asientos
Home-page: https://github.com/OCA/l10n-spain
Author: Spanish Localization Team, NaN·Tic, Trey, Tecnativa, Odoo Community Association (OCA)
Author-email: support@odoo-community.org
License: AGPL-3
Platform: UNKNOWN
Requires-Dist: odoo (<9.1a,>=9.0a)
Classifier: Programming Language :: Python :: 2.7
Classifier: Framework :: Odoo
Classifier: License :: OSI Approved :: GNU Affero General Public License v3
